{
  "cssFn": [{
      "moduleSpecifier": "@atlaskit/menu"
    },
    {
      "moduleSpecifier": "@atlaskit/side-navigation"
    }
  ],
  "overrides": [{
      "moduleSpecifier": "@atlaskit/menu"
    },
    {
      "moduleSpecifier": "@atlaskit/side-navigation"
    },
    {
      "moduleSpecifier": "@atlaskit/drawer"
    }
  ],
  "type": [{
    "moduleSpecifier": "@atlaskit/inline-message"
  }],
  "textColor": [{
    "moduleSpecifier": "@atlaskit/logo"

  }],
  "iconColor": [{
    "moduleSpecifier": "@atlaskit/logo"
  }],
  "iconGradientStart": [{
    "moduleSpecifier": "@atlaskit/logo"
  }],
  "iconGradientStop": [{
    "moduleSpecifier": "@atlaskit/logo"
  }]

}
